README.md
setup-dev.py
setup.py
deebotozmo/__init__.py
deebotozmo/cli.py
deebotozmo/constants.py
deebotozmo/ecovacsiotmq.py
deebotozmo/map.py
deebotozmodev.egg-info/PKG-INFO
deebotozmodev.egg-info/SOURCES.txt
deebotozmodev.egg-info/dependency_links.txt
deebotozmodev.egg-info/entry_points.txt
deebotozmodev.egg-info/requires.txt
deebotozmodev.egg-info/top_level.txt