Metadata-Version: 2.1
Name: deebotozmodev
Version: 0.0.2
Summary: a library for controlling certain robot vacuums [DEV edition]
Home-page: UNKNOWN
Author: Andrea Liosi
Author-email: andrea.liosi@gmail.com
License: GPL-3.0
Keywords: home automation vacuum robot
Platform: UNKNOWN
Classifier: Development Status :: 3 - Alpha
Classifier: Intended Audience :: Developers
Classifier: Topic :: Software Development :: Libraries
Classifier: Topic :: Home Automation
Classifier: License :: OSI Approved :: GNU General Public License v3 (GPLv3)
Classifier: Programming Language :: Python :: 3.5
Provides-Extra: dev
